{
  "aor": 0.00039543726235741444,
  "aqi": 0.04517679391634981,
  "bids_meta": {
    "RepetitionTime": 1,
    "TaskName": "story1",
    "dataset": "ds001338",
    "modality": "bold",
    "subject_id": "tb3810",
    "task_id": "story1"
  },
  "dummy_trs": 0,
  "dvars_nstd": 59.45114384973336,
  "dvars_std": 1.0990354118285717,
  "dvars_vstd": 0.9903737689142863,
  "efc": 0.5244950557541073,
  "fber": 2911.41455078125,
  "fd_mean": 0.13500230874980204,
  "fd_num": 47,
  "fd_perc": 8.935361216730039,
  "fwhm_avg": 1.8348449999999998,
  "fwhm_x": 1.767405,
  "fwhm_y": 2.00512,
  "fwhm_z": 1.73201,
  "gcor": 0.00217276,
  "gsr_x": 0.0006126211956143379,
  "gsr_y": 0.03097870945930481,
  "provenance": {
    "md5sum": "0ae3bbb5361f0298af6ec6f4aaa91ea1",
    "settings": {
      "fd_thres": 0.2,
      "testing": false
    },
    "software": "mriqc",
    "version": "22.0.0rc1",
    "webapi_port": null,
    "webapi_url": "https://mriqc.nimh.nih.gov/api/v1"
  },
  "size_t": 526,
  "size_x": 110,
  "size_y": 110,
  "size_z": 60,
  "snr": 5.946167044281074,
  "spacing_tr": 1.0,
  "spacing_x": 2.0,
  "spacing_y": 2.0,
  "spacing_z": 2.0,
  "summary_bg_k": 32.269133354381225,
  "summary_bg_mad": 5.7203491931853545,
  "summary_bg_mean": 20.90848159790039,
  "summary_bg_median": 8.10360050201416,
  "summary_bg_n": 475671.0,
  "summary_bg_p05": 2.9919097423553467,
  "summary_bg_p95": 79.39194869995117,
  "summary_bg_stdv": 38.31568908691406,
  "summary_fg_k": 2.3753637042494056,
  "summary_fg_mad": 63.22659596468467,
  "summary_fg_mean": 437.703125,
  "summary_fg_median": 437.3020324707031,
  "summary_fg_n": 156699.0,
  "summary_fg_p05": 325.5065399169922,
  "summary_fg_p95": 554.1384765625,
  "summary_fg_stdv": 73.54328155517578,
  "tsnr": 23.519861221313477
}