{
  "aor": 0.00018237642585551328,
  "aqi": 0.044936695247148294,
  "bids_meta": {
    "RepetitionTime": 1,
    "TaskName": "story1",
    "dataset": "ds001338",
    "modality": "bold",
    "subject_id": "tb3858",
    "task_id": "story1"
  },
  "dummy_trs": 0,
  "dvars_nstd": 53.99462632651434,
  "dvars_std": 1.0861693755428583,
  "dvars_vstd": 1.0046590814476195,
  "efc": 0.5039697029858159,
  "fber": 3477.617431640625,
  "fd_mean": 0.07641901560079022,
  "fd_num": 1,
  "fd_perc": 0.19011406844106463,
  "fwhm_avg": 1.8528000000000002,
  "fwhm_x": 1.755465,
  "fwhm_y": 2.01976,
  "fwhm_z": 1.783175,
  "gcor": 0.00311911,
  "gsr_x": -0.011949911713600159,
  "gsr_y": 0.030805524438619614,
  "provenance": {
    "md5sum": "6cfb77c044855e5e237c9dbc1bfde3aa",
    "settings": {
      "fd_thres": 0.2,
      "testing": false
    },
    "software": "mriqc",
    "version": "22.0.0rc1",
    "webapi_port": null,
    "webapi_url": "https://mriqc.nimh.nih.gov/api/v1"
  },
  "size_t": 526,
  "size_x": 110,
  "size_y": 110,
  "size_z": 60,
  "snr": 7.205437666461733,
  "spacing_tr": 1.0,
  "spacing_x": 2.0,
  "spacing_y": 2.0,
  "spacing_z": 2.0,
  "summary_bg_k": 28.668586505260368,
  "summary_bg_mad": 4.579593511528861,
  "summary_bg_mean": 18.925899505615234,
  "summary_bg_median": 7.215456962585449,
  "summary_bg_n": 492550.0,
  "summary_bg_p05": 3.185953140258789,
  "summary_bg_p95": 73.13299827575682,
  "summary_bg_stdv": 35.301700592041016,
  "summary_fg_k": 4.544346181837449,
  "summary_fg_mad": 48.48264898789187,
  "summary_fg_mean": 427.6655578613281,
  "summary_fg_median": 428.9546813964844,
  "summary_fg_n": 141337.0,
  "summary_fg_p05": 336.7707214355469,
  "summary_fg_p95": 514.7420166015625,
  "summary_fg_stdv": 59.53186798095703,
  "tsnr": 28.21529769897461
}